README.md
setup.py
src/decidim/__init__.py
src/decidim/electionguard/__init__.py
src/decidim/electionguard/bulletin_board.py
src/decidim/electionguard/common.py
src/decidim/electionguard/dummy_scheduler.py
src/decidim/electionguard/messages.py
src/decidim/electionguard/serializable.py
src/decidim/electionguard/trustee.py
src/decidim/electionguard/utils.py
src/decidim/electionguard/voter.py
src/decidim_electionguard.egg-info/PKG-INFO
src/decidim_electionguard.egg-info/SOURCES.txt
src/decidim_electionguard.egg-info/dependency_links.txt
src/decidim_electionguard.egg-info/requires.txt
src/decidim_electionguard.egg-info/top_level.txt